nonebot_plugin_fishing/__init__.py
nonebot_plugin_fishing/config.py
nonebot_plugin_fishing/data_source.py
nonebot_plugin_fishing/model.py
nonebot_plugin_fishing/migrations/68463f3e5f33_.py
nonebot_plugin_fishing/migrations/7609e6d106dd_init_db.py
nonebot_plugin_fishing/migrations/e9015df43907_add_special_fishes_field.py
nonebot_plugin_fishing/migrations/f70bdeaec7a4_add_specialfishes_table.py
nonebot_plugin_fishing-0.2.3.dist-info/LICENSE
nonebot_plugin_fishing-0.2.3.dist-info/METADATA
nonebot_plugin_fishing-0.2.3.dist-info/WHEEL
nonebot_plugin_fishing-0.2.3.dist-info/top_level.txt
nonebot_plugin_fishing-0.2.3.dist-info/RECORD
