Metadata-Version: 2.1
Name: nonebot-plugin-fishing
Version: 0.2.3
Summary: 你甚至可以电子钓鱼
Author-email: C14H22O <160833462+C14H22O@users.noreply.github.com>
License: MIT
Requires-Python: >=3.8
License-File: LICENSE
Requires-Dist: nonebot2 >=2.2.1
Requires-Dist: pydantic >=1.10
Requires-Dist: nonebot-plugin-localstore >=0.6.0
Requires-Dist: sqlalchemy >=2.0.27
Requires-Dist: aiosqlite >=0.20.0
Requires-Dist: nonebot-plugin-orm >=0.7.1
